setup.py
trayify/__init__.py
trayify/gtk_icon.py
trayify/qt_icon.py
trayify.egg-info/PKG-INFO
trayify.egg-info/SOURCES.txt
trayify.egg-info/dependency_links.txt
trayify.egg-info/top_level.txt