Metadata-Version: 1.0
Name: trayify
Version: 0.0.2
Summary: A python module for super simple system tray applications
Home-page: http://kmwhite.github.com/trayify/
Author: Kristofer M White
Author-email: me@kmwhite.net
License: BSD
Keywords: system tray gtk qt
Platform: UNKNOWN
